anopool/__init__.py
anopool/_common.py
anopool/async_pool.py
anopool/exceptions.py
anopool/pool.py
anopool/py.typed
anopool-0.1.0b0.dist-info/LICENSE
anopool-0.1.0b0.dist-info/WHEEL
anopool-0.1.0b0.dist-info/METADATA
anopool-0.1.0b0.dist-info/RECORD
