Metadata-Version: 2.1
Name: anopool
Version: 0.1.0b0
Summary: Generic thread-safe sync and async object pools.
Home-page: https://github.com/willtrnr/anopool
License: MIT
Keywords: anopool,pool,pooling
Author: William Turner
Author-email: william.turner@aero.bombardier.com
Requires-Python: >=3.6.2,<4.0.0
Classifier: Development Status :: 4 - Beta
Classifier: License :: OSI Approved :: MIT License
Classifier: Programming Language :: Python :: 3
Classifier: Programming Language :: Python :: 3.7
Classifier: Programming Language :: Python :: 3.8
Classifier: Programming Language :: Python :: 3.9
Project-URL: Repository, https://github.com/willtrnr/anopool
